archiver/__init__.py
archiver/archiver.py
archiver/config.py
archiver/tweet_api_two.py
archiver/video_download.py
config/__init__.py
config/config.py
database/__init__.py
database/database.py
experimental/__init__.py
experimental/analysis/__init__.py
experimental/analysis/analyze_tweets.py
experimental/analysis/plot_sentiment.py
experimental/cleanup/__init__.py
experimental/cleanup/remove-existing-ids.py
experimental/http2/__init__.py
experimental/http2/http2.py
experimental/import/__init__.py
experimental/import/conversations_ids.py
experimental/import/import_accounts.py
experimental/import/import_deleted_tweets.py
experimental/import/missing_tweets.py
experimental/streaming/__init__.py
experimental/streaming/streaming.py
experimental/wayback/__init__.py
experimental/wayback/add_wayback_pages.py
experimental/wayback/conversation.py
experimental/wayback/submit_pages.py
experimental/wayback/wayback.py
rover/__init__.py
rover/config.py
rover/handle_commands.py
rover/hostility_analysis.py
rover/rover.py
rover/search_tweets.py
rover/commands/__init__.py
rover/commands/analyze.py
rover/commands/hello.py
rover/commands/help.py
rover/commands/image.py
rover/commands/link.py
rover/commands/search.py
rover/server/__init__.py
rover/server/api_handler.py
rover/server/helper_functions.py
rover/server/page_handler.py
rover/server/schema_handler.py
rover/server/server.py
DigitalRover-0.0.1.dist-info/METADATA
DigitalRover-0.0.1.dist-info/WHEEL
DigitalRover-0.0.1.dist-info/top_level.txt
DigitalRover-0.0.1.dist-info/RECORD
