Metadata-Version: 2.1
Name: DigitalRover
Version: 0.0.1
Summary: Tweet archiver for use with doltpy (awaiting conversion to be able to be installed as a module)
Home-page: https://github.com/alexis-evelyn/Rover
Author: Alexis Evelyn
Author-email: alexis.a.evelyn+pypip@gmail.com
License: UNKNOWN
Project-URL: Bug Tracker, https://github.com/alexis-evelyn/Rover/issues
Platform: UNKNOWN
Classifier: Programming Language :: Python :: 3
Classifier: License :: OSI Approved :: MIT License
Classifier: Operating System :: OS Independent
Requires-Python: >=3.9
Requires-Dist: anonymizeip (==1.0.0)
Requires-Dist: certifi (==2020.12.5)
Requires-Dist: chardet (==4.0.0)
Requires-Dist: click (==7.1.2)
Requires-Dist: cx-Oracle (==8.1.0)
Requires-Dist: decorator (==4.4.2)
Requires-Dist: doltpy (==1.1.10)
Requires-Dist: idna (==2.10)
Requires-Dist: IP2Location (==8.5.1)
Requires-Dist: IP2Proxy (==3.0.0)
Requires-Dist: joblib (==1.0.0)
Requires-Dist: mysql (==0.0.2)
Requires-Dist: mysql-connector-python (==8.0.21)
Requires-Dist: mysqlclient (==2.0.3)
Requires-Dist: nltk (==3.5)
Requires-Dist: numpy (==1.19.5)
Requires-Dist: oauthlib (==3.1.0)
Requires-Dist: pandas (==1.2.1)
Requires-Dist: Pillow (==8.1.0)
Requires-Dist: protobuf (==3.14.0)
Requires-Dist: psutil (==5.8.0)
Requires-Dist: psycopg2-binary (==2.8.6)
Requires-Dist: py (==1.10.0)
Requires-Dist: PyPika (==0.47.4)
Requires-Dist: python-dateutil (==2.8.1)
Requires-Dist: pytz (==2020.5)
Requires-Dist: regex (==2020.11.13)
Requires-Dist: requests (==2.25.1)
Requires-Dist: requests-oauthlib (==1.3.0)
Requires-Dist: retry (==0.9.2)
Requires-Dist: six (==1.15.0)
Requires-Dist: SQLAlchemy (==1.3.22)
Requires-Dist: subresource-integrity (==0.2)
Requires-Dist: textblob (==0.15.3)
Requires-Dist: tqdm (==4.56.0)
Requires-Dist: urllib3 (==1.26.3)
Requires-Dist: youtube-dl (==2021.1.24.1)
